flex_ansible/__init__.py
flex_ansible/command/__init__.py
flex_ansible/command/wrapper/__init__.py
flex_ansible/command/wrapper/ansible.py
flex_ansible/command/wrapper.py
flex_cli/__init__.py
flex_cli/__main__.py
flex_cli/application/__init__.py
flex_cli/application/cli.py
flex_cli/application/flex_cli.py
flex_cli/command/__init__.py
flex_cli/command/wrapper/__init__.py
flex_cli/command/wrapper.py
flex_cli/config/__init__.py
flex_cli/etc/__init__.py
flex_cli/etc/config.py
flex_cli/etc/env.py
flex_cli/handler/__init__.py
flex_cli/handler/bash.py
flex_cli/handler/debug.py
flex_cli/handler/shell_proxy.py
flex_cli/handler/standalone_executable.py
flex_framework/__init__.py
flex_framework/api/__init__.py
flex_framework/api/application.py
flex_framework/api/command/__init__.py
flex_framework/api/command/input.py
flex_framework/api/command.py
flex_framework/api/config.py
flex_framework/api/conroller.py
flex_framework/api/exception.py
flex_framework/api/factory.py
flex_framework/api/handler.py
flex_framework/api/proxy.py
flex_framework/api/service.py
flex_framework/application/__init__.py
flex_framework/application/constants.py
flex_framework/application/response.py
flex_framework/application.py
flex_framework/config/__init__.py
flex_framework/config/deployment/__init__.py
flex_framework/config/deployment/directories.py
flex_framework/config/discover/__init__.py
flex_framework/config/exception.py
flex_framework/config/merge.py
flex_framework/config/model.py
flex_framework/config/reader/__init__.py
flex_framework/config/reader/yaml.py
flex_framework/console/__init__.py
flex_framework/console/handler.py
flex_framework/console/input.py
flex_framework/console/otput.py
flex_framework/environment/__init__.py
flex_framework/environment/manager.py
flex_framework/exceptions.py
flex_framework/filesystem.py
flex_framework/interface.py
flex_framework/loader.py
flex_framework/logger.py
flex_framework/object_manager.py
flex_framework/shell/.bashrc
flex_framework/shell/__init__.py
flex_cli-0.3.7.dist-info/LICENSE
flex_cli-0.3.7.dist-info/METADATA
flex_cli-0.3.7.dist-info/WHEEL
flex_cli-0.3.7.dist-info/entry_points.txt
flex_cli-0.3.7.dist-info/RECORD
