Metadata-Version: 2.1
Name: flex-cli
Version: 0.3.7
Summary: Local CLI is an extendable interactive command line tool built in mind with the objective to make the interaction with day to day scripts more user friendly. The scripts you use daily should be easy to maintain, develop and document so you don't need to worry to write long documents on how to use them.
Home-page: https://github.com/a42ss/lcli
License: MIT
Keywords: cli,flex,documentation,automation,local,command,command-line,script,scripts,command-line-tool,automation-framework,flex cli,flexible
Author: George Babarus
Author-email: george.babarus@gmail.com
Requires-Python: >=3.8,<4.0
Classifier: License :: OSI Approved :: MIT License
Classifier: Programming Language :: Python :: 3
Classifier: Programming Language :: Python :: 3.8
Classifier: Programming Language :: Python :: 3.9
Classifier: Programming Language :: Python :: 3.10
Classifier: Programming Language :: Python :: 3.11
Provides-Extra: ansible
Requires-Dist: PyYAML (>=6.0,<7.0)
Requires-Dist: ansible (>=6.4,<7.0) ; extra == "ansible"
Requires-Dist: blessings (>=1.7,<2.0)
Requires-Dist: fire (>=0.4,<0.6)
Requires-Dist: jsonschema (>=4.5,<5.0)
Requires-Dist: pinject (>=0.14,<0.15)
Requires-Dist: prompt-toolkit (>=3.0,<4.0)
Requires-Dist: pyfiglet (>=0.8,<0.9)
Requires-Dist: python-dotenv (>=1.0,<2.0)
Requires-Dist: setuptools (>=68.2,<69.0)
Requires-Dist: types-PyYAML
Project-URL: Repository, https://github.com/a42ss/lcli
